<?xml version="1.0" encoding="UTF-8"?>
<PeakList>
  <PeakList1D>
    <PeakList1DHeader creator="nmr" date="2023-10-12T02:53:16.918-07:00" expNo="1" name="ads_062" owner="" procNo="1" source="C:/Bruker/TopSpin3.6.0/data/kpatel/nmr">
      <PeakPickDetails>F1=16.163521ppm, F2=-3.862022ppm, MI=0.10cm, MAXI=10000.00cm, PC=1.000
      </PeakPickDetails>
    </PeakList1DHeader>
    <Peak1D F1="12.593369" intensity="3.680855e-001" type="0"/>
    <Peak1D F1="11.984048" intensity="3.723903e-001" type="0"/>
    <Peak1D F1="8.106921" intensity="5.403520e-001" type="0"/>
    <Peak1D F1="7.458693" intensity="4.662678e-001" type="0"/>
    <Peak1D F1="7.339116" intensity="3.907417e-001" type="0"/>
    <Peak1D F1="7.286814" intensity="3.990262e-001" type="0"/>
    <Peak1D F1="7.254860" intensity="4.372572e-001" type="0"/>
    <Peak1D F1="7.222924" intensity="4.990345e-001" type="0"/>
    <Peak1D F1="7.028048" intensity="4.008228e-001" type="0"/>
    <Peak1D F1="6.924121" intensity="3.781512e-001" type="0"/>
    <Peak1D F1="6.840903" intensity="4.248180e-001" type="0"/>
    <Peak1D F1="6.822149" intensity="4.047274e-001" type="0"/>
    <Peak1D F1="6.774921" intensity="3.863248e-001" type="0"/>
    <Peak1D F1="6.696362" intensity="3.982882e-001" type="0"/>
    <Peak1D F1="6.652132" intensity="3.977921e-001" type="0"/>
    <Peak1D F1="6.632999" intensity="4.241073e-001" type="0"/>
    <Peak1D F1="6.604894" intensity="4.057274e-001" type="0"/>
    <Peak1D F1="6.546525" intensity="4.611032e-001" type="0"/>
    <Peak1D F1="6.503195" intensity="7.878355e-001" type="0"/>
    <Peak1D F1="6.465934" intensity="4.919696e-001" type="0"/>
    <Peak1D F1="6.457133" intensity="4.904043e-001" type="0"/>
    <Peak1D F1="6.430819" intensity="5.679187e-001" type="0"/>
    <Peak1D F1="6.425094" intensity="4.955693e-001" type="0"/>
    <Peak1D F1="6.409118" intensity="5.088654e-001" type="0"/>
    <Peak1D F1="6.327257" intensity="7.529512e-001" type="0"/>
    <Peak1D F1="6.301126" intensity="6.867482e-001" type="0"/>
    <Peak1D F1="6.249477" intensity="7.602493e-001" type="0"/>
    <Peak1D F1="6.201416" intensity="8.440187e-001" type="0"/>
    <Peak1D F1="6.115750" intensity="8.976983e-001" type="0"/>
    <Peak1D F1="6.095409" intensity="8.699542e-001" type="0"/>
    <Peak1D F1="6.057656" intensity="9.355162e-001" type="0"/>
    <Peak1D F1="6.016773" intensity="1.067248e+000" type="0"/>
    <Peak1D F1="5.966139" intensity="1.095071e+000" type="0"/>
    <Peak1D F1="5.883679" intensity="1.301200e+000" type="0"/>
    <Peak1D F1="5.845193" intensity="1.426589e+000" type="0"/>
    <Peak1D F1="5.821220" intensity="1.422653e+000" type="0"/>
    <Peak1D F1="5.700369" intensity="2.483078e+000" type="0"/>
    <Peak1D F1="5.599003" intensity="6.348887e+000" type="0"/>
    <Peak1D F1="5.510277" intensity="6.215635e+000" type="0"/>
    <Peak1D F1="5.478399" intensity="6.494225e+000" type="0"/>
    <Peak1D F1="5.360193" intensity="7.811383e+000" type="0"/>
    <Peak1D F1="5.255475" intensity="1.056889e+001" type="0"/>
    <Peak1D F1="4.848890" intensity="5.777204e+003" type="0"/>
    <Peak1D F1="4.126408" intensity="8.937941e-001" type="0"/>
    <Peak1D F1="4.052665" intensity="4.366700e+000" type="0"/>
    <Peak1D F1="4.001019" intensity="4.227706e+000" type="0"/>
    <Peak1D F1="3.948797" intensity="5.577139e+000" type="0"/>
    <Peak1D F1="3.919449" intensity="6.298879e+000" type="0"/>
    <Peak1D F1="3.880925" intensity="6.689891e+000" type="0"/>
    <Peak1D F1="3.812982" intensity="7.358323e+000" type="0"/>
    <Peak1D F1="3.633066" intensity="1.306620e+001" type="0"/>
    <Peak1D F1="3.573758" intensity="1.426423e+001" type="0"/>
    <Peak1D F1="3.479980" intensity="3.639265e+001" type="0"/>
    <Peak1D F1="3.477313" intensity="3.716957e+001" type="0"/>
    <Peak1D F1="3.307808" intensity="3.935076e+003" type="0"/>
    <Peak1D F1="3.305118" intensity="3.995947e+003" type="0"/>
    <Peak1D F1="3.130838" intensity="1.257694e+001" type="0"/>
    <Peak1D F1="3.128104" intensity="1.295455e+001" type="0"/>
    <Peak1D F1="2.645508" intensity="5.715950e-001" type="0"/>
    <Peak1D F1="2.627316" intensity="5.946870e-001" type="0"/>
    <Peak1D F1="2.603635" intensity="8.065288e-001" type="0"/>
    <Peak1D F1="2.587538" intensity="9.283764e-001" type="0"/>
    <Peak1D F1="2.557470" intensity="1.667649e+000" type="0"/>
    <Peak1D F1="2.551537" intensity="1.034977e+000" type="0"/>
    <Peak1D F1="2.534682" intensity="1.084404e+000" type="0"/>
    <Peak1D F1="2.529318" intensity="6.079144e-001" type="0"/>
    <Peak1D F1="2.506230" intensity="5.853736e-001" type="0"/>
    <Peak1D F1="2.495502" intensity="6.512393e-001" type="0"/>
    <Peak1D F1="2.431156" intensity="7.868496e-001" type="0"/>
    <Peak1D F1="2.414511" intensity="1.016002e+000" type="0"/>
    <Peak1D F1="2.401128" intensity="1.160795e+000" type="0"/>
    <Peak1D F1="2.386775" intensity="1.047156e+000" type="0"/>
    <Peak1D F1="2.347301" intensity="8.219724e-001" type="0"/>
    <Peak1D F1="2.326482" intensity="1.202638e+000" type="0"/>
    <Peak1D F1="2.308177" intensity="1.887279e+000" type="0"/>
    <Peak1D F1="2.289188" intensity="1.661543e+000" type="0"/>
    <Peak1D F1="2.270847" intensity="1.542354e+000" type="0"/>
    <Peak1D F1="2.241251" intensity="8.275369e-001" type="0"/>
    <Peak1D F1="2.215723" intensity="8.060771e-001" type="0"/>
    <Peak1D F1="2.162264" intensity="1.474474e+000" type="0"/>
    <Peak1D F1="2.120292" intensity="1.613031e+000" type="0"/>
    <Peak1D F1="2.098727" intensity="1.059424e+000" type="0"/>
    <Peak1D F1="2.059879" intensity="1.061168e+000" type="0"/>
    <Peak1D F1="2.041488" intensity="1.301259e+000" type="0"/>
    <Peak1D F1="2.017182" intensity="8.713066e+000" type="0"/>
    <Peak1D F1="1.986162" intensity="2.857913e+000" type="0"/>
    <Peak1D F1="1.915851" intensity="7.014410e-001" type="0"/>
    <Peak1D F1="1.889290" intensity="7.754716e-001" type="0"/>
    <Peak1D F1="1.877519" intensity="1.377575e+000" type="0"/>
    <Peak1D F1="1.801185" intensity="6.749027e-001" type="0"/>
    <Peak1D F1="1.766057" intensity="8.232480e-001" type="0"/>
    <Peak1D F1="1.759559" intensity="8.683584e-001" type="0"/>
    <Peak1D F1="1.739861" intensity="8.348693e-001" type="0"/>
    <Peak1D F1="1.596749" intensity="2.334552e+000" type="0"/>
    <Peak1D F1="1.534958" intensity="1.849307e+000" type="0"/>
    <Peak1D F1="1.520225" intensity="1.915579e+000" type="0"/>
    <Peak1D F1="1.423256" intensity="2.293228e+000" type="0"/>
    <Peak1D F1="1.404711" intensity="2.691834e+000" type="0"/>
    <Peak1D F1="1.382907" intensity="3.335911e+000" type="0"/>
    <Peak1D F1="1.375062" intensity="4.208206e+000" type="0"/>
    <Peak1D F1="1.345374" intensity="4.438501e+000" type="0"/>
    <Peak1D F1="1.293398" intensity="1.457043e+001" type="0"/>
    <Peak1D F1="1.288382" intensity="1.500000e+001" type="0"/>
    <Peak1D F1="1.264322" intensity="5.709208e+000" type="0"/>
    <Peak1D F1="1.235574" intensity="4.033624e+000" type="0"/>
    <Peak1D F1="1.223330" intensity="7.868454e+000" type="0"/>
    <Peak1D F1="1.202266" intensity="4.898003e+000" type="0"/>
    <Peak1D F1="1.186512" intensity="4.551868e+000" type="0"/>
    <Peak1D F1="1.121961" intensity="1.722273e+000" type="0"/>
    <Peak1D F1="1.099137" intensity="1.496984e+000" type="0"/>
    <Peak1D F1="1.045638" intensity="1.286215e+000" type="0"/>
    <Peak1D F1="1.011042" intensity="1.501827e+000" type="0"/>
    <Peak1D F1="0.996539" intensity="1.623366e+000" type="0"/>
    <Peak1D F1="0.993029" intensity="1.655998e+000" type="0"/>
    <Peak1D F1="0.946560" intensity="1.892532e+000" type="0"/>
    <Peak1D F1="0.914110" intensity="3.028773e+000" type="0"/>
    <Peak1D F1="0.897739" intensity="3.981448e+000" type="0"/>
    <Peak1D F1="0.880681" intensity="2.285705e+000" type="0"/>
    <Peak1D F1="0.835055" intensity="9.070967e-001" type="0"/>
    <Peak1D F1="0.146348" intensity="6.875590e+000" type="0"/>
    <Peak1D F1="0.104515" intensity="5.452227e+000" type="0"/>
    <Peak1D F1="0.095762" intensity="9.139846e+001" type="0"/>
    <Peak1D F1="0.086791" intensity="1.895743e+001" type="0"/>
    <Peak1D F1="0.083828" intensity="2.517450e+001" type="0"/>
    <Peak1D F1="0.080856" intensity="2.346866e+001" type="0"/>
    <Peak1D F1="0.057204" intensity="3.191700e+000" type="0"/>
    <Peak1D F1="0.044429" intensity="3.199582e+000" type="0"/>
    <Peak1D F1="0.010205" intensity="3.625860e+001" type="0"/>
    <Peak1D F1="0.007880" intensity="4.461203e+001" type="0"/>
    <Peak1D F1="0.002094" intensity="1.193318e+003" type="0"/>
    <Peak1D F1="-0.000153" intensity="1.325088e+003" type="0"/>
    <Peak1D F1="-0.149128" intensity="8.211669e+000" type="0"/>
    <Peak1D F1="-0.174232" intensity="1.840596e+000" type="0"/>
    <Peak1D F1="-0.221946" intensity="1.407523e+000" type="0"/>
    <Peak1D F1="-0.243302" intensity="1.287771e+000" type="0"/>
    <Peak1D F1="-0.302414" intensity="9.108744e-001" type="0"/>
    <Peak1D F1="-0.333204" intensity="8.049012e-001" type="0"/>
    <Peak1D F1="-0.379212" intensity="5.867984e-001" type="0"/>
    <Peak1D F1="-0.403692" intensity="6.894099e-001" type="0"/>
    <Peak1D F1="-0.438364" intensity="5.301332e-001" type="0"/>
    <Peak1D F1="-0.455799" intensity="5.225548e-001" type="0"/>
    <Peak1D F1="-0.473498" intensity="4.680952e-001" type="0"/>
    <Peak1D F1="-0.484817" intensity="4.184716e-001" type="0"/>
    <Peak1D F1="-0.541782" intensity="3.790774e-001" type="0"/>
    <Peak1D F1="-3.168686" intensity="4.480068e-001" type="0"/>
    <Peak1D F1="-3.230581" intensity="3.818651e-001" type="0"/>
    <Peak1D F1="-3.324523" intensity="4.080651e-001" type="0"/>
    <Peak1D F1="-3.396397" intensity="4.244256e-001" type="0"/>
    <Peak1D F1="-3.566023" intensity="4.986712e-001" type="0"/>
    <Peak1D F1="-3.617808" intensity="4.125441e-001" type="0"/>
    <Peak1D F1="-3.694806" intensity="3.856613e-001" type="0"/>
  </PeakList1D>
</PeakList>
